defichain_exporter/__init__.py
defichain_exporter/__main__.py
defichain_exporter-0.0.1.dist-info/LICENSE.md
defichain_exporter-0.0.1.dist-info/METADATA
defichain_exporter-0.0.1.dist-info/WHEEL
defichain_exporter-0.0.1.dist-info/entry_points.txt
defichain_exporter-0.0.1.dist-info/top_level.txt
defichain_exporter-0.0.1.dist-info/RECORD
