Metadata-Version: 2.1
Name: defichain-exporter
Version: 0.0.1
Summary: DefiChain exporter for Prometheus
Home-page: https://github.com/sandrich/defichain_exporter
Author: Christian Sandrini
Author-email: mail@chrissandrini.ch
License: UNKNOWN
Keywords: python,defichain,exporter
Platform: UNKNOWN
Classifier: Development Status :: 3 - Alpha
Classifier: Programming Language :: Python :: 3
Classifier: Operating System :: POSIX :: Linux
Requires-Dist: jsonrpc-requests
Requires-Dist: prometheus-client
